julime/__init__.py
julime-1.1.0.dist-info/licenses/LICENSE
julime-1.1.0.dist-info/METADATA
julime-1.1.0.dist-info/WHEEL
julime-1.1.0.dist-info/top_level.txt
julime-1.1.0.dist-info/RECORD
