Metadata-Version: 2.4
Name: julime
Version: 1.1.0
Summary: JuLime is part of GeoLime ecosystem
Author-email: DeepLime <contact@deeplime.io>
Project-URL: Homepage, https://github.com/deeplime-io/julime-pypi-package
Project-URL: Repository, https://github.com/deeplime-io/julime-pypi-package
Keywords: julime,geolime,geostats
Classifier: Programming Language :: Python :: 3
Classifier: Operating System :: OS Independent
Requires-Python: >=3.8
License-File: LICENSE
Dynamic: license-file
